codeforge/__init__.py
codeforge/__module_timing__.py
codeforge/_modidx.py
codeforge/_nbdev.py
codeforge/adapters.py
codeforge/bb_utils.py
codeforge/bokeh_loader.py
codeforge/charts.py
codeforge/checkpoint.py
codeforge/cli.py
codeforge/dates.py
codeforge/decorators.py
codeforge/fastcores.py
codeforge/icecream.py
codeforge/imgaug_loader.py
codeforge/inspector.py
codeforge/interactive_show.py
codeforge/ipython.py
codeforge/load_defaults.py
codeforge/loader.py
codeforge/logger.py
codeforge/markup.py
codeforge/markup2.py
codeforge/misc.py
codeforge/paths.py
codeforge/pdf_loader.py
codeforge/registry.py
codeforge/s3_loader.py
codeforge/scp.py
codeforge/sklegos.py
codeforge/text_utils.py
codeforge/tmp.py
codeforge/torch_loader.py
codeforge/video.py
codeforge/zen.py
codeforge/thinc_parser/__init__.py
codeforge/thinc_parser/parser.py
codeforge/trainer/__init__.py
codeforge/trainer/capsule.py
codeforge/trainer/config.py
codeforge/trainer/hooks.py
codeforge/trainer/neural_graph.py
codeforge-0.0.14.dist-info/LICENSE
codeforge-0.0.14.dist-info/METADATA
codeforge-0.0.14.dist-info/WHEEL
codeforge-0.0.14.dist-info/top_level.txt
codeforge-0.0.14.dist-info/RECORD
